peewee_sanic_rest/__init__.py
peewee_sanic_rest/core.py
peewee_sanic_rest/exceptions.py
peewee_sanic_rest/filters.py
peewee_sanic_rest-0.0.1.dist-info/DESCRIPTION.rst
peewee_sanic_rest-0.0.1.dist-info/METADATA
peewee_sanic_rest-0.0.1.dist-info/RECORD
peewee_sanic_rest-0.0.1.dist-info/WHEEL
peewee_sanic_rest-0.0.1.dist-info/metadata.json
peewee_sanic_rest-0.0.1.dist-info/top_level.txt
tests/__init__.py
