Metadata-Version: 2.0
Name: peewee-sanic-rest
Version: 0.0.1
Summary: UNKNOWN
Home-page: https://github.com/_/peewee-sanic-rest
Author: Valian
Author-email: jakub.skalecki@gmail.com
License: MIT
Keywords: peewee,sanic,rest,crud
Platform: UNKNOWN
Classifier: Development Status :: 4 - Beta
Classifier: Intended Audience :: Developers
Classifier: License :: OSI Approved :: MIT License
Classifier: Natural Language :: English
Classifier: Operating System :: OS Independent
Classifier: Programming Language :: Python :: 3.5
Classifier: Programming Language :: Python :: 3.6
Classifier: Programming Language :: Python :: Implementation :: CPython
Requires-Dist: marshmallow-peewee
Requires-Dist: peewee-async
Requires-Dist: sanic
